motapi/__init__.py
motapi/motdata.py
motapi/ratelimit.py
mot_history_api_py_sdk-1.0.3.dist-info/LICENSE
mot_history_api_py_sdk-1.0.3.dist-info/METADATA
mot_history_api_py_sdk-1.0.3.dist-info/WHEEL
mot_history_api_py_sdk-1.0.3.dist-info/top_level.txt
mot_history_api_py_sdk-1.0.3.dist-info/RECORD
