Metadata-Version: 2.1
Name: mot-history-api-py-sdk
Version: 1.0.3
Summary: The SDK provides convenient access to the MOT History API for applications written in the Python programming language.
Home-page: https://documentation.history.mot.api.gov.uk/
Author: Finbarrs Oketunji
Author-email: f@finbarrs.eu
License: MIT
Project-URL: Bug Tracker, https://github.com/0xnu/mot-history-api-sdk/issues
Project-URL: Changes, https://github.com/0xnu/mot-history-api-sdk/blob/main/CHANGELOG.md
Project-URL: Documentation, https://documentation.history.mot.api.gov.uk/
Project-URL: Source Code, https://github.com/0xnu/mot-history-api-sdk
Keywords: dvsa,gov,uk,mot,hgv,psv,vehicle,registration,results
Classifier: Development Status :: 5 - Production/Stable
Classifier: Intended Audience :: Developers
Classifier: License :: OSI Approved :: MIT License
Classifier: Operating System :: OS Independent
Classifier: Programming Language :: Python
Classifier: Programming Language :: Python :: 2
Classifier: Programming Language :: Python :: 2.7
Classifier: Programming Language :: Python :: 3
Classifier: Programming Language :: Python :: 3.4
Classifier: Programming Language :: Python :: 3.5
Classifier: Programming Language :: Python :: 3.6
Classifier: Programming Language :: Python :: 3.7
Classifier: Programming Language :: Python :: 3.8
Classifier: Programming Language :: Python :: 3.9
Classifier: Programming Language :: Python :: 3.10
Classifier: Programming Language :: Python :: 3.11
Classifier: Programming Language :: Python :: Implementation :: PyPy
Classifier: Topic :: Software Development :: Libraries :: Python Modules
Requires-Python: >=2.7, !=3.0.*, !=3.1.*, !=3.2.*, !=3.3.*
License-File: LICENSE
Requires-Dist: requests
